__init__.py
core.py
formats.py
lazy.py
nagata-0.1.6.dist-info/METADATA
nagata-0.1.6.dist-info/WHEEL
nagata-0.1.6.dist-info/licenses/LICENSE
nagata-0.1.6.dist-info/RECORD
