Metadata-Version: 2.1
Name: nagata
Version: 0.1.6
Summary: python file management using a common, intuitive syntax
Keywords: factory construction constructor design pattern
Author-Email: Corey Rayburn Yung <coreyrayburnyung@gmail.com>
License: Apache-2.0
Classifier: Development Status :: 4 - Beta
Classifier: Intended Audience :: Developers
Classifier: Programming Language :: Python
Classifier: Programming Language :: Python :: 3
Classifier: Programming Language :: Python :: 3 :: Only
Classifier: Programming Language :: Python :: 3.9
Classifier: Programming Language :: Python :: 3.10
Classifier: Programming Language :: Python :: 3.11
Classifier: Topic :: Software Development
Classifier: Topic :: Utilities
Classifier: Typing :: Typed
Project-URL: Documentation, https://WithPrecedent.github.io/nagata
Project-URL: Repository, https://github.com/WithPrecedent/nagata
Project-URL: Issues, https://github.com/WithPrecedent/nagata/issues
Project-URL: Discussions, https://github.com/WithPrecedent/nagata/discussions
Project-URL: Changelog, https://WithPrecedent.github.io/nagata/changelog
Requires-Python: >=3.9
Requires-Dist: camina
Requires-Dist: miller
